coinpaprika/__init__.py
coinpaprika/client.py
coinpaprika/exceptions.py
coinpaprika_sdk-1.0.0.dist-info/LICENSE
coinpaprika_sdk-1.0.0.dist-info/METADATA
coinpaprika_sdk-1.0.0.dist-info/WHEEL
coinpaprika_sdk-1.0.0.dist-info/top_level.txt
coinpaprika_sdk-1.0.0.dist-info/RECORD
