Metadata-Version: 2.1
Name: coinpaprika-sdk
Version: 1.0.0
Summary: Official coinpaprika API Python client
Home-page: https://github.com/coinpaprika/coinpaprika-api-python-client
Author: Coinpaprika
Author-email: coinpaprika <it@coinpaprika.com>
License: Apache License 2.0
Project-URL: Homepage, https://github.com/coinpaprika/coinpaprika-api-python-client
Project-URL: Bug Tracker, https://github.com/coinpaprika/coinpaprika-api-python-client/issues
Keywords: coinpaprika api cryptocurrency
Classifier: Programming Language :: Python :: 3
Classifier: License :: OSI Approved :: Apache Software License
Classifier: Operating System :: OS Independent
Requires-Python: >=3.7
License-File: LICENSE
Requires-Dist: requests
